django_vue_utilities/__init__.py
django_vue_utilities/templatetags/__init__.py
django_vue_utilities/templatetags/vue_utils.py
django_vue_utilities/tests/__init__.py
django_vue_utilities/tests/settings.py
django_vue_utils-0.1.7.dist-info/LICENSE
django_vue_utils-0.1.7.dist-info/METADATA
django_vue_utils-0.1.7.dist-info/WHEEL
django_vue_utils-0.1.7.dist-info/top_level.txt
django_vue_utils-0.1.7.dist-info/RECORD
