Metadata-Version: 2.1
Name: django-vue-utils
Version: 0.1.7
Summary: Utilities and helpers for integrating Django + Vue
Home-page: https://github.com/ilikerobots/django-vue-utils
Author: Mike Hoolehan
Author-email: Mike Hoolehan <mike@starheightmedia.com>
License: MIT
Project-URL: Homepage, https://github.com/ilikerobots/django-vue-utils
Project-URL: Bug Tracker, https://github.com/ilikerobots/django-vue-utils/issues
Classifier: Environment :: Web Environment
Classifier: Framework :: Django
Classifier: Intended Audience :: Developers
Classifier: License :: OSI Approved :: MIT License
Classifier: Operating System :: OS Independent
Classifier: Programming Language :: Python
Classifier: Programming Language :: Python :: 3
Classifier: Programming Language :: JavaScript
Requires-Python: >=3.7
License-File: LICENSE
Requires-Dist: Django >=3.2
